axaiogram/__init__.py
axaiogram/settings.py
axaiogram/db/__init__.py
axaiogram/db/models.py
axaiogram/db/schemas.py
axaiogram/db/repository/__init__.py
axaiogram/db/repository/collection.py
axaiogram/db/repository/user.py
axaiogram/db/repository/user_lang.py
axaiogram/handlers/__init__.py
axaiogram/handlers/base.py
axaiogram/handlers/frozen_handler.py
axaiogram/handlers/auth/__init__.py
axaiogram/handlers/auth/email_user_auth_handlers.py
axaiogram/handlers/collection/__init__.py
axaiogram/handlers/collection/collection.py
axaiogram/handlers/user/__init__.py
axaiogram/handlers/user/language_setup.py
axaiogram/middlewares/__init__.py
axaiogram/middlewares/template_middleware.py
axaiogram/middlewares/user_language_middleware.py
axaiogram/middlewares/auth/__init__.py
axaiogram/middlewares/auth/on_the_fly_user_auth_middleware.py
axaiogram/middlewares/auth/use_handler_user_auth_middleware.py
axaiogram/static/__init__.py
axaiogram/static/messages_group.py
axaiogram/templates/__init__.py
axaiogram/templates/collection.py
axaiogram/templates/html_parser.py
axaiogram/templates/template_group.py
axaiogram/templates/template_group_factory.py
axaiogram/templates/template_message.py
axaiogram/templates/template_parser.py
axaiogram/tests/__init__.py
axaiogram/tests/test_md_parser.py
axaiogram/utils/__init__.py
axaiogram/utils/handler.py
axaiogram/utils/keyboard.py
axaiogram/utils/keyboard_pagination.py
axaiogram/utils/types.py
axaiogram-0.0.44.dist-info/METADATA
axaiogram-0.0.44.dist-info/WHEEL
axaiogram-0.0.44.dist-info/top_level.txt
axaiogram-0.0.44.dist-info/RECORD
