Metadata-Version: 2.1
Name: axaiogram
Version: 0.0.44
Summary: library developed on top of aiogram framework that adds bunch of reuseable features
Author: axdjuraev
Author-email: <axdjuraev@gmail.com>
Requires-Dist: aiogram ==3.0.0b7
Requires-Dist: axabc >=0.0.1
Requires-Dist: axsqlalchemy >=0.0.1
